.gitignore
LICENSE
MANIFEST.in
README.md
pyproject.toml
setup.py
.github/dependabot.yml
.github/issue_template.md
.github/workflows/pythonpackage.yml
docs/Makefile
docs/source/conf.py
docs/source/index.rst
docs/source/tutorials/comparison-with-pyrb.ipynb
docs/source/tutorials/including-mean-return-and-variance.ipynb
docs/source/tutorials/index.rst
docs/source/tutorials/minimal-usage.ipynb
riskparityportfolio.egg-info/PKG-INFO
riskparityportfolio.egg-info/SOURCES.txt
riskparityportfolio.egg-info/dependency_links.txt
riskparityportfolio.egg-info/not-zip-safe
riskparityportfolio.egg-info/top_level.txt
src/riskparityportfolio/__init__.py
src/riskparityportfolio/my_tests.py
src/riskparityportfolio/riskfunctions.py
src/riskparityportfolio/rpp.py
src/riskparityportfolio/sca.py
src/riskparityportfolio/vanilla.cpp
src/riskparityportfolio/vanilla.h
src/riskparityportfolio/version.py
src/riskparityportfolio/examples/main.cpp
src/riskparityportfolio/tests/__init__.py
src/riskparityportfolio/tests/test_modern_rpp.py
src/riskparityportfolio/tests/test_vanilla_rpp.py
third-party/eigen_3.3.7/.hg_archival.txt
third-party/eigen_3.3.7/.hgeol
third-party/eigen_3.3.7/.hgignore
third-party/eigen_3.3.7/.hgtags
third-party/eigen_3.3.7/CMakeLists.txt
third-party/eigen_3.3.7/COPYING.BSD
third-party/eigen_3.3.7/COPYING.GPL
third-party/eigen_3.3.7/COPYING.LGPL
third-party/eigen_3.3.7/COPYING.MINPACK
third-party/eigen_3.3.7/COPYING.MPL2
third-party/eigen_3.3.7/COPYING.README
third-party/eigen_3.3.7/CTestConfig.cmake
third-party/eigen_3.3.7/CTestCustom.cmake.in
third-party/eigen_3.3.7/INSTALL
third-party/eigen_3.3.7/README.md
third-party/eigen_3.3.7/eigen3.pc.in
third-party/eigen_3.3.7/signature_of_eigen3_matrix_library
third-party/eigen_3.3.7/Eigen/CMakeLists.txt
third-party/eigen_3.3.7/Eigen/Cholesky
third-party/eigen_3.3.7/Eigen/CholmodSupport
third-party/eigen_3.3.7/Eigen/Core
third-party/eigen_3.3.7/Eigen/Dense
third-party/eigen_3.3.7/Eigen/Eigen
third-party/eigen_3.3.7/Eigen/Eigenvalues
third-party/eigen_3.3.7/Eigen/Geometry
third-party/eigen_3.3.7/Eigen/Householder
third-party/eigen_3.3.7/Eigen/IterativeLinearSolvers
third-party/eigen_3.3.7/Eigen/Jacobi
third-party/eigen_3.3.7/Eigen/LU
