Metadata-Version: 2.1
Name: riskparityportfolio
Version: 0.6.0
Summary: Blazingly fast design of risk parity portfolios
Home-page: https://github.com/dppalomar/riskparity.py
Author: Ze Vinicius & Dani Palomar
Author-email: jvmirca@gmail.com
License: MIT
Classifier: Development Status :: 3 - Alpha
Classifier: Intended Audience :: Financial and Insurance Industry
Classifier: License :: OSI Approved :: MIT License
Classifier: Operating System :: OS Independent
Classifier: Programming Language :: Python :: 3.0
License-File: LICENSE
